simctl_mcp_server.py
simctl_mcp_server-0.1.0.dist-info/licenses/LICENSE
simctl_mcp_server-0.1.0.dist-info/METADATA
simctl_mcp_server-0.1.0.dist-info/WHEEL
simctl_mcp_server-0.1.0.dist-info/entry_points.txt
simctl_mcp_server-0.1.0.dist-info/top_level.txt
simctl_mcp_server-0.1.0.dist-info/RECORD
